README.rst
setup.py
sqlew/__init__.py
sqlew/client.py
sqlew/compat.py
sqlew/exceptions.py
sqlew/queryformat.py
sqlew/restructables.py
sqlew.egg-info/PKG-INFO
sqlew.egg-info/SOURCES.txt
sqlew.egg-info/dependency_links.txt
sqlew.egg-info/top_level.txt