Metadata-Version: 1.1
Name: sqlew
Version: 1.1.0
Summary: db client
Home-page: http://github.com/tomokinakamaru/sqlew
Author: Tomoki Nakamaru
Author-email: tomoki.nakamaru@gmail.com
License: MIT
Platform: any
Classifier: Development Status :: 4 - Beta
Classifier: Intended Audience :: Developers
Classifier: License :: OSI Approved :: MIT License
Classifier: Programming Language :: Python
Classifier: Topic :: Database :: Front-Ends
Classifier: Topic :: Software Development :: Libraries :: Python Modules
